tidy_json_to_csv.py
tidy_json_to_csv-0.0.13.dist-info/LICENSE
tidy_json_to_csv-0.0.13.dist-info/METADATA
tidy_json_to_csv-0.0.13.dist-info/WHEEL
tidy_json_to_csv-0.0.13.dist-info/entry_points.txt
tidy_json_to_csv-0.0.13.dist-info/top_level.txt
tidy_json_to_csv-0.0.13.dist-info/RECORD
