Metadata-Version: 2.1
Name: tidy-json-to-csv
Version: 0.0.13
Summary: Convert JSON to a set of tidy CSV files
Home-page: https://github.com/uktrade/tidy-json-to-csv
Author: Department for International Trade
Author-email: webops@digital.trade.gov.uk
License: UNKNOWN
Platform: UNKNOWN
Classifier: Programming Language :: Python :: 3
Classifier: License :: OSI Approved :: MIT License
Classifier: Operating System :: OS Independent
Requires-Python: >=3.6.3
Requires-Dist: ijson (<4,>=3.0.4)
